printandlog/__init__.py
printandlog/definition.py
printandlog/printandlog.py
printandlog-0.2.dist-info/DESCRIPTION.rst
printandlog-0.2.dist-info/METADATA
printandlog-0.2.dist-info/RECORD
printandlog-0.2.dist-info/WHEEL
printandlog-0.2.dist-info/metadata.json
printandlog-0.2.dist-info/top_level.txt
