Metadata-Version: 2.0
Name: printandlog
Version: 0.2
Summary: Print on output and on a unique log file 
Home-page: https://github.com/Tibibv/printandlog
Author: Kron
Author-email: kron_bv@yahoo.com
License: MIT
Platform: UNKNOWN
